cruscopoetry/syllabifiers/wol/__init__.py
cruscopoetry/syllabifiers/wol/__main__.py
cruscopoetry/syllabifiers/wol/syllabificator.py
cruscopoetry/syllabifiers/wol/syllabifier.py
cruscopoetry/syllabifiers/wol/syllable.py
cruscopoetry.syllabifiers.wol-0.0.2.dist-info/METADATA
cruscopoetry.syllabifiers.wol-0.0.2.dist-info/WHEEL
cruscopoetry.syllabifiers.wol-0.0.2.dist-info/top_level.txt
cruscopoetry.syllabifiers.wol-0.0.2.dist-info/RECORD
